csgapi/__init__.py
csgapi/base.py
csgapi/client.py
csgapi/mixin.py
csgapi/setup.py
csgapi/types.py
csgapi/utils.py
csgapi/objects/__init__.py
csgapi/objects/accelerator_configuration.py
csgapi/objects/application.py
csgapi/objects/architecture.py
csgapi/objects/benchmarks.py
csgapi/objects/codename.py
csgapi/objects/continent.py
csgapi/objects/contribution.py
csgapi/objects/contribution_category.py
csgapi/objects/contribution_name.py
csgapi/objects/contributor.py
csgapi/objects/contributor_source.py
csgapi/objects/coprocessors.py
csgapi/objects/country.py
csgapi/objects/degree_type.py
csgapi/objects/ethnicity.py
csgapi/objects/file_system.py
csgapi/objects/firmware.py
csgapi/objects/floating_point_unit.py
csgapi/objects/from_country.py
csgapi/objects/genera.py
csgapi/objects/graphics_cards.py
csgapi/objects/green500.py
csgapi/objects/has_accelerator.py
csgapi/objects/has_contribution_name.py
csgapi/objects/has_education.py
csgapi/objects/has_ethnicity.py
csgapi/objects/has_interconnect.py
csgapi/objects/has_memory.py
csgapi/objects/has_operating_system.py
csgapi/objects/has_organization.py
csgapi/objects/has_processor.py
csgapi/objects/has_race.py
csgapi/objects/interconnect.py
csgapi/objects/interconnect_configuration.py
csgapi/objects/interconnect_family.py
csgapi/objects/isas.py
csgapi/objects/manufacturer.py
csgapi/objects/memory_configuration.py
csgapi/objects/microarchitectures.py
csgapi/objects/ontology_type.py
csgapi/objects/operating_system.py
csgapi/objects/operating_system_configuration.py
csgapi/objects/organization.py
csgapi/objects/other_software.py
csgapi/objects/pointer.py
csgapi/objects/processor_configuration.py
csgapi/objects/processor_hierarchy.py
csgapi/objects/processors.py
csgapi/objects/race.py
csgapi/objects/region.py
csgapi/objects/resource.py
csgapi/objects/segment.py
csgapi/objects/source.py
csgapi/objects/spec1995.py
csgapi/objects/spec2000.py
csgapi/objects/spec2006.py
csgapi/objects/spec2017.py
csgapi/objects/system_configuration.py
csgapi-0.1.7.dist-info/METADATA
csgapi-0.1.7.dist-info/WHEEL
csgapi-0.1.7.dist-info/top_level.txt
csgapi-0.1.7.dist-info/RECORD
