Metadata-Version: 2.1
Name: csgapi
Version: 0.1.7
Summary: API for interacting with the Computer Systems Genome database.
Home-page: https://csgenome.org/
Author: Computer Systems Genome
Author-email: csgenomevtteam@gmail.com
License: MIT
Platform: UNKNOWN
Classifier: Intended Audience :: Developers
Classifier: License :: OSI Approved :: MIT License
Classifier: Programming Language :: Python
Classifier: Programming Language :: Python :: 3
Classifier: Programming Language :: Python :: 3.10
Classifier: Operating System :: OS Independent
Requires-Dist: flask
Requires-Dist: requests
